LICENSE
README.rst
jsonfeed/__init__.py
jsonfeed/__version__.py
jsonfeed/core.py
django_jsonfeed-0.4.0.dist-info/LICENSE
django_jsonfeed-0.4.0.dist-info/WHEEL
django_jsonfeed-0.4.0.dist-info/METADATA
django_jsonfeed-0.4.0.dist-info/RECORD
