Metadata-Version: 2.1
Name: django-jsonfeed
Version: 0.4.0
Summary: JSONFeed syndication in Django.
Home-page: https://github.com/myles/django-jsonfeed
License: MIT
Author: Myles Braithwaite
Author-email: me@mylesbraithwaite.org
Requires-Python: >=3.8,<4.0
Classifier: Framework :: Django
Classifier: Framework :: Flask
Classifier: Framework :: Pelican
Classifier: License :: OSI Approved :: MIT License
Classifier: Programming Language :: Python
Classifier: Programming Language :: Python :: 3
Classifier: Programming Language :: Python :: 3.10
Classifier: Programming Language :: Python :: 3.8
Classifier: Programming Language :: Python :: 3.9
Project-URL: Repository, https://github.com/myles/django-jsonfeed
